lineagesim/__init__.py
lineagesim/output.py
lineagesim/population.py
lineagesim/run_lineagesim.py
lineagesim-0.2.2.dist-info/DESCRIPTION.rst
lineagesim-0.2.2.dist-info/METADATA
lineagesim-0.2.2.dist-info/RECORD
lineagesim-0.2.2.dist-info/WHEEL
lineagesim-0.2.2.dist-info/entry_points.txt
lineagesim-0.2.2.dist-info/metadata.json
lineagesim-0.2.2.dist-info/top_level.txt
